django_user_images/__init__.py
django_user_images/admin.py
django_user_images/apps.py
django_user_images/models.py
django_user_images/settings.py
django_user_images/migrations/0001_initial.py
django_user_images/migrations/0002_auto_20180609_0601.py
django_user_images/migrations/__init__.py
django_user_images/rest/__init__.py
django_user_images/rest/admin.py
django_user_images/rest/api.py
django_user_images/rest/apps.py
django_user_images/rest/models.py
django_user_images/rest/serializers.py
django_user_images/rest/tests.py
django_user_images/rest/migrations/__init__.py
django_user_images-0.1.0.dist-info/DESCRIPTION.rst
django_user_images-0.1.0.dist-info/METADATA
django_user_images-0.1.0.dist-info/RECORD
django_user_images-0.1.0.dist-info/WHEEL
django_user_images-0.1.0.dist-info/metadata.json
django_user_images-0.1.0.dist-info/top_level.txt
