Metadata-Version: 2.0
Name: django-user-images
Version: 0.1.0
Summary: Django app for managing user files uploads and permissions
Home-page: https://github.com/zlebnik/django-user-images
Author: Gleb Kovalev
Author-email: gleb@popmechanic.ru
License: MIT
Keywords: django-user-images
Platform: UNKNOWN
Classifier: Development Status :: 3 - Alpha
Classifier: Framework :: Django :: 1.11
Classifier: Framework :: Django :: 2.0
Classifier: Intended Audience :: Developers
Classifier: License :: OSI Approved :: BSD License
Classifier: Natural Language :: English
Classifier: Programming Language :: Python :: 2
Classifier: Programming Language :: Python :: 2.7
Classifier: Programming Language :: Python :: 3
Classifier: Programming Language :: Python :: 3.4
Classifier: Programming Language :: Python :: 3.5
Classifier: Programming Language :: Python :: 3.6
Requires-Dist: django-model-utils (>=2.0)
